Metadata-Version: 2.1
Name: financial_calculator_4
Version: 0.1.0
Summary: Крутой пакет
Author-email: euschevlyakova <euschevlyakova@yandex.ru>
License: MIT
Requires-Python: >=3.12
Requires-Dist: argparse>=3.2
